odoo/addons/pos_access_right/README.rst
odoo/addons/pos_access_right/__init__.py
odoo/addons/pos_access_right/__manifest__.py
odoo/addons/pos_access_right/demo/res_groups.xml
odoo/addons/pos_access_right/i18n/ar.po
odoo/addons/pos_access_right/i18n/ca.po
odoo/addons/pos_access_right/i18n/es.po
odoo/addons/pos_access_right/i18n/fr.po
odoo/addons/pos_access_right/i18n/it.po
odoo/addons/pos_access_right/i18n/pos_access_right.pot
odoo/addons/pos_access_right/i18n/ru.po
odoo/addons/pos_access_right/models/__init__.py
odoo/addons/pos_access_right/models/pos_config.py
odoo/addons/pos_access_right/models/pos_session.py
odoo/addons/pos_access_right/readme/CONFIGURE.rst
odoo/addons/pos_access_right/readme/CONTRIBUTORS.rst
odoo/addons/pos_access_right/readme/DESCRIPTION.rst
odoo/addons/pos_access_right/readme/USAGE.rst
odoo/addons/pos_access_right/security/res_groups.xml
odoo/addons/pos_access_right/static/description/admin_numpad.png
odoo/addons/pos_access_right/static/description/demo_error.png
odoo/addons/pos_access_right/static/description/demo_numpad.png
odoo/addons/pos_access_right/static/description/icon.png
odoo/addons/pos_access_right/static/description/index.html
odoo/addons/pos_access_right/static/description/new_groups.png
odoo/addons/pos_access_right/static/src/css/pos.css
odoo/addons/pos_access_right/static/src/js/ActionpadWidget.js
odoo/addons/pos_access_right/static/src/js/NumpadWidget.js
odoo/addons/pos_access_right/static/src/js/TicketScreen.js
odoo/addons/pos_access_right/static/src/xml/ActionpadWidget.xml
odoo/addons/pos_access_right/static/src/xml/NumpadWidget.xml
odoo/addons/pos_access_right/static/src/xml/TicketScreen.xml
odoo/addons/pos_access_right/tests/__init__.py
odoo/addons/pos_access_right/tests/test_pos_access_right.py
odoo_addon_pos_access_right-16.0.1.0.2.dist-info/METADATA
odoo_addon_pos_access_right-16.0.1.0.2.dist-info/WHEEL
odoo_addon_pos_access_right-16.0.1.0.2.dist-info/top_level.txt
odoo_addon_pos_access_right-16.0.1.0.2.dist-info/RECORD
